merge_front_back/__init__.py
merge_front_back/merge_front_back.py
merge_front_back-1.0.0b2.dist-info/entry_points.txt
merge_front_back-1.0.0b2.dist-info/WHEEL
merge_front_back-1.0.0b2.dist-info/METADATA
merge_front_back-1.0.0b2.dist-info/RECORD
