Metadata-Version: 2.4
Name: merge-front-back
Version: 1.0.0b2
Summary: Merge two single-sided scanned PDFs into a duplex document
Author-email: Doug Ransom <doug@ransom.vip>
Requires-Python: >=3.14
Requires-Dist: pypdf>=4.0.0
